zoon/__init__.py
zoon/decoder.py
zoon/encoder.py
zoon/types.py
zoon_format-1.0.3.dist-info/METADATA
zoon_format-1.0.3.dist-info/WHEEL
zoon_format-1.0.3.dist-info/entry_points.txt
zoon_format-1.0.3.dist-info/RECORD
