Metadata-Version: 2.4
Name: zoon-format
Version: 1.0.3
Summary: ZOON - Zero Overhead Object Notation for LLM context optimization
Project-URL: Homepage, https://github.com/zoon-format/zoon
Project-URL: Repository, https://github.com/zoon-format/zoon
Author: Carsen Klock
License: MIT
Keywords: ai,compression,context-window,json,llm,tokens
Classifier: Development Status :: 4 - Beta
Classifier: Intended Audience :: Developers
Classifier: License :: OSI Approved :: MIT License
Classifier: Programming Language :: Python :: 3
Classifier: Programming Language :: Python :: 3.10
Classifier: Programming Language :: Python :: 3.11
Classifier: Programming Language :: Python :: 3.12
Classifier: Topic :: Software Development :: Libraries :: Python Modules
Requires-Python: >=3.10
